shaclc/__init__.py
shaclc/grammar.lark
shaclc/parser.py
shaclc/serializer.py
shaclc-0.1.1.dist-info/LICENSE
shaclc-0.1.1.dist-info/METADATA
shaclc-0.1.1.dist-info/WHEEL
shaclc-0.1.1.dist-info/RECORD
