Metadata-Version: 2.1
Name: shaclc
Version: 0.1.1
Summary: A Python SHACL Compact Syntax parser and serializer.
Home-page: https://github.com/edmondchuc/shaclc
License: MIT
Keywords: RDF,SHACL,Python
Author: Edmond Chuc
Author-email: edmond.chuc@outlook.com
Requires-Python: >=3.10
Classifier: Environment :: Web Environment
Classifier: Intended Audience :: Developers
Classifier: License :: OSI Approved :: MIT License
Classifier: Operating System :: OS Independent
Classifier: Programming Language :: Python
Classifier: Programming Language :: Python :: 3
Classifier: Programming Language :: Python :: 3.10
Classifier: Programming Language :: Python :: 3.11
Classifier: Programming Language :: Python :: 3.12
Classifier: Topic :: Internet :: WWW/HTTP :: Dynamic Content
Classifier: Topic :: Software Development :: Libraries :: Python Modules
Requires-Dist: lark (>=1.1.8,<2.0.0)
Requires-Dist: rdflib (>=7.0.0,<8.0.0)
Project-URL: Repository, https://github.com/edmondchuc/shaclc
